matos_gcp_provider/__init__.py
matos_gcp_provider/config.py
matos_gcp_provider/gcp_filter.py
matos_gcp_provider/observation.py
matos_gcp_provider/provider.py
matos_gcp_provider/lib/__init__.py
matos_gcp_provider/lib/auth.py
matos_gcp_provider/lib/base_provider.py
matos_gcp_provider/lib/factory.py
matos_gcp_provider/lib/loader.py
matos_gcp_provider/lib/utils.py
matos_gcp_provider/plugins/__init__.py
matos_gcp_provider/plugins/apiKeys.py
matos_gcp_provider/plugins/auditLogs.py
matos_gcp_provider/plugins/cluster.py
matos_gcp_provider/plugins/iam.py
matos_gcp_provider/plugins/instance.py
matos_gcp_provider/plugins/orgPolicy.py
matos_gcp_provider/plugins/serviceAccount.py
matos_gcp_provider/plugins/storage.py
matos_gcp_provider-1.0.12.dist-info/LICENSE
matos_gcp_provider-1.0.12.dist-info/METADATA
matos_gcp_provider-1.0.12.dist-info/WHEEL
matos_gcp_provider-1.0.12.dist-info/top_level.txt
matos_gcp_provider-1.0.12.dist-info/RECORD
