Metadata-Version: 2.1
Name: matos-gcp-provider
Version: 1.0.12
Summary: Python matos gcp provider
Author: matos community
Author-email: community@cloudmatos.com
Project-URL: Bug Reports, https://github.com/cloudmatos/matos-gcp-provider/issues
Project-URL: Source, https://github.com/cloudmatos/matos-gcp-provider
Keywords: aws,cloudsecurity,matos,cloudmatos
Classifier: Development Status :: 3 - Alpha
Classifier: Intended Audience :: Developers
Classifier: Topic :: Software Development :: Build Tools
Classifier: License :: OSI Approved :: MIT License
Classifier: Programming Language :: Python :: 3
Classifier: Programming Language :: Python :: 3.7
Classifier: Programming Language :: Python :: 3.8
Classifier: Programming Language :: Python :: 3.9
Classifier: Programming Language :: Python :: 3.10
Classifier: Programming Language :: Python :: 3 :: Only
Requires-Python: >=3.7, <4
License-File: LICENSE
Requires-Dist: protobuf (==3.19.1)
Requires-Dist: google-api-core
Requires-Dist: google-api-python-client (==2.33.0)
Requires-Dist: google-auth (==2.3.3)
Requires-Dist: google-auth-httplib2 (==0.1.0)
Requires-Dist: google-cloud (==0.34.0)
Requires-Dist: google-cloud-access-context-manager (==0.1.9)
Requires-Dist: google-cloud-asset (==3.7.1)
Requires-Dist: google-cloud-container (==2.10.1)
Requires-Dist: google-cloud-core (==2.2.1)
Requires-Dist: google-cloud-monitoring (==2.8.0)
Requires-Dist: google-cloud-org-policy (==1.2.1)
Requires-Dist: google-cloud-os-config (==1.9.0)
Requires-Dist: google-cloud-storage (==1.43.0)
Requires-Dist: google-crc32c (==1.3.0)
Requires-Dist: google-resumable-media (==2.1.0)
Requires-Dist: googleapis-common-protos
Requires-Dist: grpc-google-iam-v1
Requires-Dist: grpcio (==1.43.0)
Requires-Dist: google-cloud-api-keys (==0.1.0)
Requires-Dist: google-cloud-service-usage (==1.4.1)
Requires-Dist: google-cloud-storage
Provides-Extra: dev
Requires-Dist: check-manifest ; extra == 'dev'
Provides-Extra: test
Requires-Dist: coverage ; extra == 'test'
